Metadata-Version: 2.1
Name: pytrend
Version: 0.3
Summary: Trend detection on stock time series data
Home-page: https://github.com/dopevog/pytrend
Author: Vedant Kothari
Author-email: dopevog@gmail.com
License: MIT License
Project-URL: Bug Reports, https://github.com/dopevog/pytrend/issues
Project-URL: Source, https://github.com/dopevog/pytrend
Keywords: trend detection,stock analysis,stock,trend analysis,stock trends,financial trends
Platform: UNKNOWN
Classifier: Development Status :: 4 - Beta
Classifier: Programming Language :: Python :: 3 :: Only
Classifier: Programming Language :: Python :: 3.6
Classifier: Programming Language :: Python :: 3.7
Classifier: Programming Language :: Python :: 3.8
Classifier: License :: OSI Approved :: MIT License
Classifier: Intended Audience :: Developers
Classifier: Topic :: Office/Business :: Financial
Classifier: Topic :: Office/Business :: Financial :: Investment
Classifier: Topic :: Scientific/Engineering :: Information Analysis
Classifier: Topic :: Software Development :: Libraries
Requires-Python: >=3
